spotifyatlas/__init__.py
spotifyatlas/baseapi.py
spotifyatlas/datastructs.py
spotifyatlas/enums.py
spotifyatlas/spotifyapi.py
spotifyatlas/resources/redirectpage.html
spotifyatlas/utils/__init__.py
spotifyatlas/utils/utils.py
spotifyatlas-1.0.0.dist-info/LICENSE
spotifyatlas-1.0.0.dist-info/METADATA
spotifyatlas-1.0.0.dist-info/WHEEL
spotifyatlas-1.0.0.dist-info/top_level.txt
spotifyatlas-1.0.0.dist-info/RECORD
