Metadata-Version: 2.1
Name: spotifyatlas
Version: 1.0.0
Summary: A pythonic wrapper for the Spotify web API.
Author-email: Leonardo Corona Garza <leocoronag@gmail.com>
License: Copyright (c) 2023 Leonardo Corona Garza
Keywords: spotify,api,wrapper,web,requests
Classifier: License :: OSI Approved :: MIT License
Classifier: Programming Language :: Python
Classifier: Programming Language :: Python :: 3
Requires-Python: >=3.7
License-File: LICENSE
Requires-Dist: requests (>=2.25.1)
